autovpn.py
autovpn-0.2.2.dist-info/LICENSE.txt
autovpn-0.2.2.dist-info/METADATA
autovpn-0.2.2.dist-info/WHEEL
autovpn-0.2.2.dist-info/entry_points.txt
autovpn-0.2.2.dist-info/top_level.txt
autovpn-0.2.2.dist-info/RECORD
